sankeysolver/__init__.py
sankeysolver/__main__.py
sankeysolver/constraints.py
sankeysolver/load_data.py
sankeysolver/sankey_error.py
sankeysolver-0.1.4.dist-info/DESCRIPTION.rst
sankeysolver-0.1.4.dist-info/METADATA
sankeysolver-0.1.4.dist-info/RECORD
sankeysolver-0.1.4.dist-info/WHEEL
sankeysolver-0.1.4.dist-info/entry_points.txt
sankeysolver-0.1.4.dist-info/metadata.json
sankeysolver-0.1.4.dist-info/top_level.txt
