Metadata-Version: 2.0
Name: sankeysolver
Version: 0.1.4
Summary: Flow network / Sankey diagram solver
Home-page: UNKNOWN
Author: Rick Lupton
Author-email: rcl33@cam.ac.uk
License: MIT
Platform: UNKNOWN
Requires-Dist: numpy
Requires-Dist: pandas
Requires-Dist: xlrd
